gym_trajectory/__init__.py
gym_trajectory/envs/__init__.py
gym_trajectory/envs/trajectory_env.py
gym_trajectory-0.1.dist-info/LICENSE
gym_trajectory-0.1.dist-info/METADATA
gym_trajectory-0.1.dist-info/WHEEL
gym_trajectory-0.1.dist-info/top_level.txt
gym_trajectory-0.1.dist-info/RECORD
