Metadata-Version: 2.1
Name: gym-trajectory
Version: 0.1
Summary: Custom environment for OpenAI gym
Home-page: https://github.com/DaKup/gym-trajectory
Author: Daniel C. Kup
Author-email: danielc@gmail.com
License: UNKNOWN
Platform: UNKNOWN
Classifier: Programming Language :: Python :: 3
Classifier: License :: OSI Approved :: MIT License
Classifier: Operating System :: OS Independent
Requires-Python: >=3.6
Requires-Dist: gym (>=0.17.3)
Requires-Dist: numpy
